Workbook

Sheet PL_Report
A1: NEXORIA COMMERCE INC.
A2: Monthly Profit & Loss Statement (Actual vs. Budget)
A3: Select Period (YYYY-MM): | B3: 2024-12 | D3: =VALUE(LEFT(B3,4)) -> 2024 | E3: =VALUE(RIGHT(B3,2)) -> 12
A5: Line Item | B5: Actual ($) | C5: Budget ($) | D5: Variance ($) | E5: Variance (%)
A7: REVENUE
A8: Product Sales | B8: =SUMIFS(Actuals!F:F, Actuals!A:A, $D$3, Actuals!B:B, $E$3, Actuals!E:E, "Product Sales") -> 193607.69 | C8: =SUMIFS(Budget!F:F, Budget!A:A, $D$3, Budget!B:B, $E$3, Budget!E:E, "Product Sales") -> 169431.07 | D8: =B8-C8 -> 24176.62 | E8: =IFERROR(D8/C8, 0) -> 0.14269295
A9: Service Revenue | B9: =SUMIFS(Actuals!F:F, Actuals!A:A, $D$3, Actuals!B:B, $E$3, Actuals!E:E, "Service Revenue") -> 58506.44 | C9: =SUMIFS(Budget!F:F, Budget!A:A, $D$3, Budget!B:B, $E$3, Budget!E:E, "Service Revenue") -> 47096.01 | D9: =B9-C9 -> 11410.43 | E9: =IFERROR(D9/C9, 0) -> 0.24228018
A10: Shipping Revenue | B10: =SUMIFS(Actuals!F:F, Actuals!A:A, $D$3, Actuals!B:B, $E$3, Actuals!E:E, "Shipping Revenue") -> 52776.6 | C10: =SUMIFS(Budget!F:F, Budget!A:A, $D$3, Budget!B:B, $E$3, Budget!E:E, "Shipping Revenue") -> 43339.08 | D10: =B10-C10 -> 9437.52 | E10: =IFERROR(D10/C10, 0) -> 0.21776004
A11: Total Revenue | B11: =SUM(B8:B10) -> 304890.73 | C11: =SUM(C8:C10) -> 259866.16 | D11: =B11-C11 -> 45024.57 | E11: =IFERROR(D11/C11, 0) -> 0.17326061
A13: COST OF GOODS SOLD
A14: Product Cost | B14: =SUMIFS(Actuals!F:F, Actuals!A:A, $D$3, Actuals!B:B, $E$3, Actuals!E:E, "Product Cost") -> 415697.57 | C14: =SUMIFS(Budget!F:F, Budget!A:A, $D$3, Budget!B:B, $E$3, Budget!E:E, "Product Cost") -> 440464.55 | D14: =C14-B14 -> 24766.98 | E14: =IFERROR(D14/C14, 0) -> 0.056229224
A15: Freight In | B15: =SUMIFS(Actuals!F:F, Actuals!A:A, $D$3, Actuals!B:B, $E$3, Actuals!E:E, "Freight In") -> 519447.97 | C15: =SUMIFS(Budget!F:F, Budget!A:A, $D$3, Budget!B:B, $E$3, Budget!E:E, "Freight In") -> 477122.19 | D15: =C15-B15 -> -42325.78 | E15: =IFERROR(D15/C15, 0) -> -0.088710567
A16: Packaging | B16: =SUMIFS(Actuals!F:F, Actuals!A:A, $D$3, Actuals!B:B, $E$3, Actuals!E:E, "Packaging") -> 473558.78 | C16: =SUMIFS(Budget!F:F, Budget!A:A, $D$3, Budget!B:B, $E$3, Budget!E:E, "Packaging") -> 472619.01 | D16: =C16-B16 -> -939.77 | E16: =IFERROR(D16/C16, 0) -> -0.0019884304
A17: Total Cost of Goods Sold | B17: =SUM(B14:B16) -> 1408704.3 | C17: =SUM(C14:C16) -> 1390205.8 | D17: =C17-B17 -> -18498.57 | E17: =IFERROR(D17/C17, 0) -> -0.013306354
A19: GROSS PROFIT | B19: =B11-B17 -> -1103813.6 | C19: =C11-C17 -> -1130339.6 | D19: =B19-C19 -> 26526 | E19: =IFERROR(D19/C19, 0) -> -0.023467284
A21: OPERATING EXPENSES
A22: Salaries | B22: =SUMIFS(Actuals!F:F, Actuals!A:A, $D$3, Actuals!B:B, $E$3, Actuals!E:E, "Salaries") -> 304371.95 | C22: =SUMIFS(Budget!F:F, Budget!A:A, $D$3, Budget!B:B, $E$3, Budget!E:E, "Salaries") -> 293589.14 | D22: =C22-B22 -> -10782.81 | E22: =IFERROR(D22/C22, 0) -> -0.036727551
A23: Marketing Spend | B23: =SUMIFS(Actuals!F:F, Actuals!A:A, $D$3, Actuals!B:B, $E$3, Actuals!E:E, "Marketing Spend") -> 480187.31 | C23: =SUMIFS(Budget!F:F, Budget!A:A, $D$3, Budget!B:B, $E$3, Budget!E:E, "Marketing Spend") -> 498532.85 | D23: =C23-B23 -> 18345.54 | E23: =IFERROR(D23/C23, 0) -> 0.036799059
A24: Software & SaaS | B24: =SUMIFS(Actuals!F:F, Actuals!A:A, $D$3, Actuals!B:B, $E$3, Actuals!E:E, "Software & SaaS") -> 478857 | C24: =SUMIFS(Budget!F:F, Budget!A:A, $D$3, Budget!B:B, $E$3, Budget!E:E, "Software & SaaS") -> 470040.04 | D24: =C24-B24 -> -8816.96 | E24: =IFERROR(D24/C24, 0) -> -0.018757891
A25: Office Rent | B25: =SUMIFS(Actuals!F:F, Actuals!A:A, $D$3, Actuals!B:B, $E$3, Actuals!E:E, "Office Rent") -> 574661.27 | C25: =SUMIFS(Budget!F:F, Budget!A:A, $D$3, Budget!B:B, $E$3, Budget!E:E, "Office Rent") -> 545685.19 | D25: =C25-B25 -> -28976.08 | E25: =IFERROR(D25/C25, 0) -> -0.05310036
A26: Travel & Entertainment | B26: =SUMIFS(Actuals!F:F, Actuals!A:A, $D$3, Actuals!B:B, $E$3, Actuals!E:E, "Travel & Entertainment") -> 490415 | C26: =SUMIFS(Budget!F:F, Budget!A:A, $D$3, Budget!B:B, $E$3, Budget!E:E, "Travel & Entertainment") -> 447771.76 | D26: =C26-B26 -> -42643.24 | E26: =IFERROR(D26/C26, 0) -> -0.095234322
A27: Professional Services | B27: =SUMIFS(Actuals!F:F, Actuals!A:A, $D$3, Actuals!B:B, $E$3, Actuals!E:E, "Professional Services") -> 416125.37 | C27: =SUMIFS(Budget!F:F, Budget!A:A, $D$3, Budget!B:B, $E$3, Budget!E:E, "Professional Services") -> 406747.98 | D27: =C27-B27 -> -9377.39 | E27: =IFERROR(D27/C27, 0) -> -0.023054546
A28: Utilities | B28: =SUMIFS(Actuals!F:F, Actuals!A:A, $D$3, Actuals!B:B, $E$3, Actuals!E:E, "Utilities") -> 447146.44 | C28: =SUMIFS(Budget!F:F, Budget!A:A, $D$3, Budget!B:B, $E$3, Budget!E:E, "Utilities") -> 403140.31 | D28: =C28-B28 -> -44006.13 | E28: =IFERROR(D28/C28, 0) -> -0.10915835
A29: Depreciation | B29: =SUMIFS(Actuals!F:F, Actuals!A:A, $D$3, Actuals!B:B, $E$3, Actuals!E:E, "Depreciation") -> 518244.68 | C29: =SUMIFS(Budget!F:F, Budget!A:A, $D$3, Budget!B:B, $E$3, Budget!E:E, "Depreciation") -> 517754.8 | D29: =C29-B29 -> -489.88 | E29: =IFERROR(D29/C29, 0) -> -0.00094616216
A30: Total Operating Expenses | B30: =SUM(B22:B29) -> 3710009 | C30: =SUM(C22:C29) -> 3583262.1 | D30: =C30-B30 -> -126746.95 | E30: =IFERROR(D30/C30, 0) -> -0.035371945
A32: NET OPERATING INCOME (EBIT) | B32: =B19-B30 -> -4813822.6 | C32: =C19-C30 -> -4713601.7 | D32: =B32-C32 -> -100220.95 | E32: =IFERROR(D32/C32, 0) -> 0.021262075

Sheet Actuals
A1: year | B1: month | C1: department | D1: gl_category | E1: gl_account | F1: amount
A2: 2023 | B2: 1 | C2: Sales | D2: COGS | E2: Freight In | F2: 12974.03
A3: 2023 | B3: 1 | C3: Marketing | D3: COGS | E3: Freight In | F3: 138639.24
A4: 2023 | B4: 1 | C4: Operations | D4: COGS | E4: Freight In | F4: 68183.75
A5: 2023 | B5: 1 | C5: Finance | D5: COGS | E5: Freight In | F5: 72720.94
A6: 2023 | B6: 1 | C6: HR | D6: COGS | E6: Freight In | F6: 71246.75
A7: 2023 | B7: 1 | C7: IT | D7: COGS | E7: Freight In | F7: 44919.74
A8: 2023 | B8: 1 | C8: Customer Service | D8: COGS | E8: Freight In | F8: 52878.96
A9: 2023 | B9: 1 | C9: Sales | D9: COGS | E9: Packaging | F9: 53987.48
A10: 2023 | B10: 1 | C10: Marketing | D10: COGS | E10: Packaging | F10: 117405.44
A11: 2023 | B11: 1 | C11: Operations | D11: COGS | E11: Packaging | F11: 49018.5
A12: 2023 | B12: 1 | C12: Finance | D12: COGS | E12: Packaging | F12: 37790.43
A13: 2023 | B13: 1 | C13: HR | D13: COGS | E13: Packaging | F13: 74914.45
... A1921: 2024 | B1921: 12 | C1921: Sales | D1921: Revenue | E1921: Shipping Revenue | F1921: 52776.6

Sheet Budget
A1: year | B1: month | C1: department | D1: gl_category | E1: gl_account | F1: amount
A2: 2023 | B2: 1 | C2: Sales | D2: COGS | E2: Freight In | F2: 10506.26
A3: 2023 | B3: 1 | C3: Marketing | D3: COGS | E3: Freight In | F3: 114378.19
A4: 2023 | B4: 1 | C4: Operations | D4: COGS | E4: Freight In | F4: 74170.42
A5: 2023 | B5: 1 | C5: Finance | D5: COGS | E5: Freight In | F5: 77225.56
A6: 2023 | B6: 1 | C6: HR | D6: COGS | E6: Freight In | F6: 76091.92
A7: 2023 | B7: 1 | C7: IT | D7: COGS | E7: Freight In | F7: 49706.06
A8: 2023 | B8: 1 | C8: Customer Service | D8: COGS | E8: Freight In | F8: 62199.07
A9: 2023 | B9: 1 | C9: Sales | D9: COGS | E9: Packaging | F9: 56641.16
A10: 2023 | B10: 1 | C10: Marketing | D10: COGS | E10: Packaging | F10: 119214.53
A11: 2023 | B11: 1 | C11: Operations | D11: COGS | E11: Packaging | F11: 58688.06
A12: 2023 | B12: 1 | C12: Finance | D12: COGS | E12: Packaging | F12: 34968.97
A13: 2023 | B13: 1 | C13: HR | D13: COGS | E13: Packaging | F13: 91436.62
... A1921: 2024 | B1921: 12 | C1921: Sales | D1921: Revenue | E1921: Shipping Revenue | F1921: 43339.08

Sheet Settings
A1: Period
A2: 2023-01
A3: 2023-02
A4: 2023-03
A5: 2023-04
A6: 2023-05
A7: 2023-06
A8: 2023-07
A9: 2023-08
A10: 2023-09
A11: 2023-10
A12: 2023-11
... A25: 2024-12
